aitech/__init__.py
aitech/infrared.py
aitech/masspsec.py
aitech/runner.py
aitech/tg_dsc.py
aitech/utils.py
aitech-0.1.2.dist-info/WHEEL
aitech-0.1.2.dist-info/METADATA
aitech-0.1.2.dist-info/RECORD
