Metadata-Version: 2.1
Name: aitech
Version: 0.1.2
Summary: 
Author: mjaquier
Author-email: mjaquier@me.com
Requires-Python: >=3.7,<4.0
Classifier: Programming Language :: Python :: 3
Classifier: Programming Language :: Python :: 3.7
Classifier: Programming Language :: Python :: 3.8
Requires-Dist: PyYAML (>=5.3.1,<6.0.0)
Requires-Dist: pandas (>=1.0.3,<2.0.0)
Requires-Dist: xlsxwriter (>=1.2.8,<2.0.0)
